{
  "date": "2025-12-08",
  "north_pole": {
    "x": 500,
    "y": 500
  },
  "houses": [
    {
      "id": 1,
      "x": 800,
      "y": 200
    },
    {
      "id": 2,
      "x": 700,
      "y": 700
    },
    {
      "id": 3,
      "x": 500,
      "y": 800
    },
    {
      "id": 4,
      "x": 600,
      "y": 200
    },
    {
      "id": 5,
      "x": 200,
      "y": 100
    },
    {
      "id": 6,
      "x": 400,
      "y": 500
    },
    {
      "id": 7,
      "x": 600,
      "y": 500
    },
    {
      "id": 8,
      "x": 100,
      "y": 900
    },
    {
      "id": 9,
      "x": 400,
      "y": 900
    },
    {
      "id": 10,
      "x": 600,
      "y": 100
    },
    {
      "id": 11,
      "x": 600,
      "y": 900
    },
    {
      "id": 12,
      "x": 700,
      "y": 500
    },
    {
      "id": 13,
      "x": 200,
      "y": 700
    },
    {
      "id": 14,
      "x": 500,
      "y": 700
    },
    {
      "id": 15,
      "x": 900,
      "y": 900
    },
    {
      "id": 16,
      "x": 300,
      "y": 200
    }
  ],
  "optimal_distance": 3746.0118234448214
}